vector_cache/__init__.py
vector_cache/main.py
vector_cache/cache_storage/__init__.py
vector_cache/cache_storage/base.py
vector_cache/cache_storage/lfu.py
vector_cache/cache_storage/lru.py
vector_cache/cache_storage/memcache.py
vector_cache/cache_storage/redis_store.py
vector_cache/embedding/__init__.py
vector_cache/embedding/base_embedding.py
vector_cache/embedding/cohere.py
vector_cache/embedding/openai.py
vector_cache/embedding/sentence_bert.py
vector_cache/embedding_similarity/__init__.py
vector_cache/error_handlers/__init__.py
vector_cache/utils/__init__.py
vector_cache/utils/key_util.py
vector_cache/utils/time_utils.py
vector_cache/vector_stores/__init__.py
vector_cache/vector_stores/base.py
vector_cache/vector_stores/chroma_db.py
vector_cache/vector_stores/deeplake.py
vector_cache/vector_stores/pgvector.py
vector_cache/vector_stores/pinecone.py
vector_cache/vector_stores/qdrant.py
vector_cache/vector_stores/redis_vector.py
vector_cache-1.1.1.dist-info/LICENSE
vector_cache-1.1.1.dist-info/METADATA
vector_cache-1.1.1.dist-info/WHEEL
vector_cache-1.1.1.dist-info/top_level.txt
vector_cache-1.1.1.dist-info/RECORD
