Metadata-Version: 2.1
Name: vector-cache
Version: 1.1.1
Summary: A streamlined Python library that enhances LLM query performance through semantic caching, making responses faster and more cost-effective.
Author: Shivendra Soni
Project-URL: Source Code, https://github.com/shivendrasoni/vector-cache
Classifier: Programming Language :: Python :: 3
Classifier: License :: OSI Approved :: MIT License
Classifier: Operating System :: OS Independent
Requires-Python: >=3.9
License-File: LICENSE
Requires-Dist: chromadb
Requires-Dist: numpy
Requires-Dist: openai
Provides-Extra: all
Requires-Dist: pymemcache ; extra == 'all'
Requires-Dist: cohere ; extra == 'all'
Requires-Dist: sentence-transformers ; extra == 'all'
Requires-Dist: psycopg2-binary ; extra == 'all'
Requires-Dist: redis ; extra == 'all'
Requires-Dist: pinecone-client ; extra == 'all'
Requires-Dist: qdrant-client ; extra == 'all'
Requires-Dist: pgvector ; extra == 'all'
Provides-Extra: cohere
Requires-Dist: cohere ; extra == 'cohere'
Provides-Extra: memcache
Requires-Dist: pymemcache ; extra == 'memcache'
Provides-Extra: pgvector
Requires-Dist: psycopg2-binary ; extra == 'pgvector'
Requires-Dist: pgvector ; extra == 'pgvector'
Provides-Extra: pinecone
Requires-Dist: pinecone-client ; extra == 'pinecone'
Provides-Extra: qdrant
Requires-Dist: qdrant-client ; extra == 'qdrant'
Provides-Extra: redis
Requires-Dist: redis ; extra == 'redis'
Provides-Extra: sentence-transformers
Requires-Dist: sentence-transformers ; extra == 'sentence-transformers'
